sftkit/__init__.py
sftkit/__main__.py
sftkit/async_thread.py
sftkit/database/__init__.py
sftkit/database/_attach.py
sftkit/database/_config.py
sftkit/database/_connection.py
sftkit/database/_database.py
sftkit/database/_hook.py
sftkit/database/_migrations.py
sftkit/database/_pool.py
sftkit/database/introspection/__init__.py
sftkit/devel/__init__.py
sftkit/devel/_cli.py
sftkit/devel/_config.py
sftkit/devel/_debian.py
sftkit/error.py
sftkit/http/__init__.py
sftkit/http/_config.py
sftkit/http/_context.py
sftkit/http/_error.py
sftkit/http/_server.py
sftkit/service.py
sftkit/util.py
sftkit-0.4.2.dist-info/WHEEL
sftkit-0.4.2.dist-info/entry_points.txt
sftkit-0.4.2.dist-info/METADATA
sftkit-0.4.2.dist-info/RECORD
