Metadata-Version: 2.3
Name: sftkit
Version: 0.4.2
Summary: ...
License: MIT
Classifier: Operating System :: OS Independent
Classifier: Programming Language :: Python :: 3
Classifier: License :: OSI Approved :: MIT License
Requires-Dist: fastapi>=0.115.10
Requires-Dist: typer>=0.15.2
Requires-Dist: uvicorn>=0.34.0
Requires-Dist: asyncpg>=0.30.0
Requires-Dist: pydantic[email]>=2.10.6
Maintainer: Michael Loipführer
Maintainer-email: Michael Loipführer <milo@sft.lol>
Requires-Python: >=3.11
Project-URL: Source, https://github.com/SFTTech/sftkit
